CONTRIBUTING.md
LICENSE
MANIFEST.in
README.md
THIRD_PARTY_LIC
setup.cfg
setup.py
boards/Pynq-atk/base/__init__.py
boards/Pynq-atk/base/base.bit
boards/Pynq-atk/base/base.hwh
boards/Pynq-atk/base/base.py
boards/Pynq-atk/base/base.tcl
boards/Pynq-atk/base/base.xdc
boards/Pynq-atk/base/build_base_dsa.tcl
boards/Pynq-atk/base/build_base_ip.tcl
boards/Pynq-atk/base/build_bitstream.tcl
boards/Pynq-atk/base/check_base.tcl
boards/Pynq-atk/base/constants.py
boards/Pynq-atk/base/notebooks/audio/audio_playback.ipynb
boards/Pynq-atk/base/notebooks/audio/recording_0.wav
boards/Pynq-atk/base/notebooks/board/asyncio_buttons.ipynb
boards/Pynq-atk/base/notebooks/board/board_btns_leds.ipynb
boards/Pynq-atk/base/notebooks/board/register_map_intro.ipynb
boards/Pynq-atk/base/notebooks/microblaze/microblaze_c_libraries.ipynb
boards/Pynq-atk/base/notebooks/microblaze/microblaze_programming.ipynb
boards/Pynq-atk/base/notebooks/microblaze/microblaze_python_libraries.ipynb
boards/Pynq-atk/base/notebooks/video/hdmi_introduction.ipynb
boards/Pynq-atk/base/notebooks/video/hdmi_video_pipeline.ipynb
boards/Pynq-atk/base/notebooks/video/opencv_face_detect_hdmi.ipynb
boards/Pynq-atk/base/notebooks/video/opencv_face_detect_webcam.ipynb
boards/Pynq-atk/base/notebooks/video/opencv_filters_hdmi.ipynb
boards/Pynq-atk/base/notebooks/video/opencv_filters_webcam.ipynb
boards/Pynq-atk/base/notebooks/video/data/face_detect.jpg
boards/Pynq-atk/base/notebooks/video/data/gray.jpg
boards/Pynq-atk/base/notebooks/video/data/haarcascade_eye.xml
boards/Pynq-atk/base/notebooks/video/data/haarcascade_frontalface_default.xml
boards/Pynq-atk/base/notebooks/video/data/opencv_filters.jpg
boards/Pynq-atk/base/notebooks/video/data/orig.jpg
boards/Pynq-atk/base/notebooks/video/data/sobel.jpg
boards/Pynq-atk/notebooks/getting_started/4_base_overlay_video.ipynb
boards/Pynq-atk/notebooks/getting_started/5_base_overlay_audio.ipynb
boards/Pynq-atk/ov5640_lcd_7010/__init__.py
boards/Pynq-atk/ov5640_lcd_7010/build_bitstream.tcl
pynq_atk.egg-info/PKG-INFO
pynq_atk.egg-info/SOURCES.txt
pynq_atk.egg-info/dependency_links.txt
pynq_atk.egg-info/entry_points.txt
pynq_atk.egg-info/not-zip-safe
pynq_atk.egg-info/requires.txt
pynq_atk.egg-info/top_level.txt