Metadata-Version: 2.1
Name: pynq-atk
Version: 2.5.5
Summary: (PY)thon productivity for zy(NQ)
Home-page: https://github.com/Xilinx/PYNQ
Author: Xilinx PYNQ Development Team
Author-email: pynq_support@xilinx.com
License: BSD 3-Clause
Download-URL: https://github.com/Xilinx/PYNQ
Platform: UNKNOWN
Requires-Python: >=3.5.2
